Metadata-Version: 2.1
Name: melvision
Version: 0.1.1
Summary: A convenient deep learning and image processing library.
Home-page: https://github.com/Manuel667399/melvision
Author: Melvin Hwang
Author-email: huang667399@gmail.com
Classifier: Programming Language :: Python :: 3
Classifier: License :: OSI Approved :: MIT License
Classifier: Operating System :: OS Independent
